pyvodb/__init__.py
pyvodb/__main__.py
pyvodb/calendar.py
pyvodb/dumpers.py
pyvodb/load.py
pyvodb/tables.py
pyvodb/cli/__init__.py
pyvodb/cli/calendar.py
pyvodb/cli/cliutil.py
pyvodb/cli/show.py
pyvodb/cli/top.py
pyvodb/cli/videometadata.py
pyvodb-1.0.dist-info/LICENSE
pyvodb-1.0.dist-info/METADATA
pyvodb-1.0.dist-info/WHEEL
pyvodb-1.0.dist-info/entry_points.txt
pyvodb-1.0.dist-info/top_level.txt
pyvodb-1.0.dist-info/RECORD
